README.rst
_imdo.c
imdo.py
setup.py
imdo.egg-info/PKG-INFO
imdo.egg-info/SOURCES.txt
imdo.egg-info/dependency_links.txt
imdo.egg-info/entry_points.txt
imdo.egg-info/top_level.txt