Metadata-Version: 1.1
Name: imdo
Version: 0.0.2
Summary: Launch a process in an identifiable session
Home-page: https://github.com/tecywiz121/imdo/
Author: Sam Wilson
Author-email: tecywiz121@hotmail.com
License: GPL3
Keywords: linux
Platform: UNKNOWN
Classifier: Development Status :: 3 - Alpha
Classifier: Intended Audience :: Developers
Classifier: License :: OSI Approved :: GNU General Public License v3 or later (GPLv3+)
Classifier: Programming Language :: Python :: 2
